lisscad/__init__.py
lisscad/__main__.py
lisscad/app.py
lisscad/exc.py
lisscad/main.py
lisscad/misc.py
lisscad/op.py
lisscad/prelude.lissp
lisscad/prelude.py
lisscad/py_to_scad.py
lisscad/data/__init__.py
lisscad/data/inter.py
lisscad/data/other.py
lisscad/data/util.py
lisscad/thread/__init__.py
lisscad/thread/_base.py
lisscad/vocab/__init__.py
lisscad/vocab/base.py
lisscad/vocab/english.py
lisscad/vocab/util.py
lisscad-0.2.0.dist-info/licenses/COPYING.md
lisscad-0.2.0.dist-info/METADATA
lisscad-0.2.0.dist-info/WHEEL
lisscad-0.2.0.dist-info/entry_points.txt
lisscad-0.2.0.dist-info/top_level.txt
lisscad-0.2.0.dist-info/RECORD
