Metadata-Version: 2.4
Name: lisscad
Version: 0.2.0
Summary: CAD in Lissp
License: GPL-3.0-only
Keywords: CAD,CSG,Lissp,OpenSCAD,code generation,geometry,lisp,modeling
Classifier: Development Status :: 2 - Pre-Alpha
Classifier: Intended Audience :: Developers
Classifier: Intended Audience :: End Users/Desktop
Classifier: Intended Audience :: Manufacturing
Classifier: License :: OSI Approved :: GNU General Public License v3 (GPLv3)
Classifier: Operating System :: OS Independent
Classifier: Programming Language :: Lisp
Classifier: Programming Language :: Python :: 3
Classifier: Topic :: Multimedia :: Graphics :: 3D Modeling
Classifier: Topic :: Software Development :: Libraries :: Application Frameworks
Requires-Python: >=3.10
License-File: COPYING.md
Requires-Dist: hissp
Requires-Dist: inotify_simple
Requires-Dist: more-itertools
Requires-Dist: pydantic
Requires-Dist: rich
Requires-Dist: typer
Dynamic: license-file
